csv_2_mongo.py
csv_2_mongo-0.0.2.dist-info/METADATA
csv_2_mongo-0.0.2.dist-info/WHEEL
csv_2_mongo-0.0.2.dist-info/entry_points.txt
csv_2_mongo-0.0.2.dist-info/top_level.txt
csv_2_mongo-0.0.2.dist-info/RECORD
