Metadata-Version: 2.1
Name: csv-2-mongo
Version: 0.0.2
Summary: Import a CSV to MongoDB.
Home-page: https://github.com/clarketm/csv_2_mongo
Author: Travis Clarke
Author-email: travis.m.clarke@gmail.com
License: UNKNOWN
Platform: UNKNOWN
Classifier: Intended Audience :: Developers
Classifier: Natural Language :: English
Classifier: Programming Language :: Python :: 3
Classifier: License :: OSI Approved :: MIT License
Classifier: Operating System :: OS Independent
Classifier: Environment :: Console
Requires-Dist: click
Requires-Dist: pandas
Requires-Dist: pymongo
Provides-Extra: dev
Requires-Dist: black; extra == 'dev'
Requires-Dist: nose2; extra == 'dev'
